{
  "version": 2,
  "extractor": "pdffigures2",
  "figures": [
    {
      "url": "assets/figures/arxiv/2606.11963v1/fig-016.webp",
      "caption": "Figure 1: Schematic overview of HAMNO and its physics-informed extension PI-HAMNO, combining multi-scale operator learning with physics-based regularization.",
      "page": 9,
      "index": 16,
      "width": 929,
      "height": 565
    },
    {
      "url": "assets/figures/arxiv/2606.11963v1/fig-013.webp",
      "caption": "Figure 2: Rollout relative L2 errors for the full neural-operator comparison on the threedimensional phase-field benchmarks: (a) AC, (b) CH, and (c) SH. The vertically stacked layout compares long-horizon predictive behavior across the governing equations while preserving readability.",
      "page": 17,
      "index": 13,
      "width": 1035,
      "height": 1198
    },
    {
      "url": "assets/figures/arxiv/2606.11963v1/fig-008.webp",
      "caption": "Figure 3: Rollout relative L2 errors of the U-shaped baselines for the three-dimensional phasefield benchmarks: (a) AC, (b) CH, and (c) SH. The comparison highlights the effect of hierarchical encoder–decoder structure without adaptive local–global fusion.",
      "page": 18,
      "index": 8,
      "width": 987,
      "height": 1102
    },
    {
      "url": "assets/figures/arxiv/2606.11963v1/fig-012.webp",
      "caption": "Figure 4: Training histories of all compared models, showing (a) total loss and (b) test relative L2 error during training.",
      "page": 19,
      "index": 12,
      "width": 795,
      "height": 458
    },
    {
      "url": "assets/figures/arxiv/2606.11963v1/fig-017.webp",
      "caption": "Figure 5: Predicted phase-field solutions at t = 100 for the AC, CH, and SH benchmarks, showing reference fields, model predictions, and the HAMNO absolute error.",
      "page": 20,
      "index": 17,
      "width": 910,
      "height": 465
    },
    {
      "url": "assets/figures/arxiv/2606.11963v1/fig-003.webp",
      "caption": "Figure 6: Free-energy decay and mass conservation for the CH benchmark under different physics weights λ.",
      "page": 21,
      "index": 3,
      "width": 910,
      "height": 519
    },
    {
      "url": "assets/figures/arxiv/2606.11963v1/fig-006.webp",
      "caption": "Table 1: Ablation study of the pure-physics HAMNO setting (λ = 1), where all reported values are mean relative L2 errors at selected rollout times.",
      "page": 22,
      "index": 6,
      "width": 929,
      "height": 327
    },
    {
      "url": "assets/figures/arxiv/2606.11963v1/fig-007.webp",
      "caption": "Table 2: OOD evaluation results for the 3D AC equation under three unseen initial-condition distributions controlled by α and τ .",
      "page": 22,
      "index": 7,
      "width": 929,
      "height": 380
    },
    {
      "url": "assets/figures/arxiv/2606.11963v1/fig-010.webp",
      "caption": "Table 3: OOD evaluation results for the 3D CH equation under unseen initial-condition distributions controlled by α and τ .",
      "page": 23,
      "index": 10,
      "width": 929,
      "height": 404
    },
    {
      "url": "assets/figures/arxiv/2606.11963v1/fig-009.webp",
      "caption": "Table 4: OOD evaluation results for the 3D SH equation under unseen initial-condition distributions controlled by α and τ .",
      "page": 23,
      "index": 9,
      "width": 929,
      "height": 379
    },
    {
      "url": "assets/figures/arxiv/2606.11963v1/fig-015.webp",
      "caption": "Table 5: Four-seed robustness summary for selected models on the AC, CH, and SH benchmarks, with Mean ± Std reporting seed statistics of the all-time mean relative L2 error.",
      "page": 24,
      "index": 15,
      "width": 779,
      "height": 896
    },
    {
      "url": "assets/figures/arxiv/2606.11963v1/fig-001.webp",
      "caption": "Table 6: Ten-seed robustness summary for HAMNO on the AC, CH, and SH benchmarks, with Mean ± Std reporting seed statistics of the all-time mean relative L2 error.",
      "page": 25,
      "index": 1,
      "width": 769,
      "height": 274
    },
    {
      "url": "assets/figures/arxiv/2606.11963v1/fig-002.webp",
      "caption": "Table 7: Neural-operator hyperparameters used for the 3D phase-field benchmarks.",
      "page": 26,
      "index": 2,
      "width": 929,
      "height": 713
    },
    {
      "url": "assets/figures/arxiv/2606.11963v1/fig-014.webp",
      "caption": "Table 8: Allen–Cahn (3D) rollout errors and computational cost.",
      "page": 27,
      "index": 14,
      "width": 929,
      "height": 819
    },
    {
      "url": "assets/figures/arxiv/2606.11963v1/fig-011.webp",
      "caption": "Table 9: Cahn–Hilliard (3D) rollout errors and computational cost.",
      "page": 28,
      "index": 11,
      "width": 929,
      "height": 819
    },
    {
      "url": "assets/figures/arxiv/2606.11963v1/fig-005.webp",
      "caption": "Table 10: Swift–Hohenberg (3D) rollout errors and computational cost.",
      "page": 29,
      "index": 5,
      "width": 929,
      "height": 819
    },
    {
      "url": "assets/figures/arxiv/2606.11963v1/fig-004.webp",
      "caption": "Table 11: Summary of the governing phase-field models and dataset parameters.",
      "page": 30,
      "index": 4,
      "width": 1008,
      "height": 1011
    }
  ]
}