{
  "version": 2,
  "extractor": "pdffigures2",
  "figures": [
    {
      "url": "assets/figures/arxiv/2606.00659v1/fig-004.webp",
      "caption": "Figure 1: (a) Maximum eigenvalues of Q/c for the semi-implicit scheme. (b) Maximum eigenvalues of Q/c for the scheme (3.5)–(3.7). (c) Number of Newton’s iteration for δt = 1.",
      "page": 22,
      "index": 4,
      "width": 931,
      "height": 267
    },
    {
      "url": "assets/figures/arxiv/2606.00659v1/fig-005.webp",
      "caption": "Figure 2: (a) Energy. (b) The concentration and eigenvalue at t = 50, computed on a mesh N = 64 and time step δt = 3.125× 10−4. The principal eigenvectors are plotted in the figure of concentration.",
      "page": 23,
      "index": 5,
      "width": 931,
      "height": 270
    },
    {
      "url": "assets/figures/arxiv/2606.00659v1/fig-006.webp",
      "caption": "Figure 3: The error ε with different (a) time steps for N = 64; and (b) spatial discretizations with δt = h2/10.",
      "page": 23,
      "index": 6,
      "width": 885,
      "height": 346
    },
    {
      "url": "assets/figures/arxiv/2606.00659v1/fig-008.webp",
      "caption": "Figure 4: Snapshots of the solution for c0 = 20 and L = √ 20. The colorbar is the same as the density profile shown in Fig.2.",
      "page": 24,
      "index": 8,
      "width": 887,
      "height": 585
    },
    {
      "url": "assets/figures/arxiv/2606.00659v1/fig-001.webp",
      "caption": "Figure 5: The steady states for (a) c0 = 5, L = √ 10; (b) c0 = 10, L = √ 10; (c) c0 = 20, L = √ 5; (d) c0 = 20, L = √ 20.",
      "page": 25,
      "index": 1,
      "width": 653,
      "height": 591
    },
    {
      "url": "assets/figures/arxiv/2606.00659v1/fig-002.webp",
      "caption": "Figure 6: The steady states for L = 4d correspond to the initial states of (a) uniform vertical alignment and (b) uniform 135◦ alignment.",
      "page": 26,
      "index": 2,
      "width": 654,
      "height": 286
    },
    {
      "url": "assets/figures/arxiv/2606.00659v1/fig-003.webp",
      "caption": "Figure 7: When the initial state consists of left-half 45◦ alignment and right-half 135◦ alignment for L = 8d, the total energy versus time is shown in (a), and (b)-(f) are snapshots of the solution evolution at t = 20, 40, 70, 120, 160. The color bar corresponds to the density profile shown in Fig.6.",
      "page": 26,
      "index": 3,
      "width": 838,
      "height": 540
    },
    {
      "url": "assets/figures/arxiv/2606.00659v1/fig-007.webp",
      "caption": "Figure 8: When the initial state is set to be 135◦ alignment for L = 8d, the total energy versus time is shown in (a), and (b)-(f) are snapshots of the solution evolution at t = 10, 30, 60, 100, 150. The colorbar follows the same scale as the density profile shown in Fig.6.",
      "page": 27,
      "index": 7,
      "width": 838,
      "height": 539
    }
  ]
}