{
  "version": 2,
  "extractor": "pdffigures2",
  "figures": [
    {
      "url": "assets/figures/arxiv/2605.26285v1/fig-001.webp",
      "caption": "Figure 3. Barotropic flow: Our two-parameter flow approach scales population-dynamics inference to turbulent systems with states in d > 104 dimensions. It learns a fast-to-evaluate population-dynamics model that bypasses fine-scale advection motion (see lower kinetic energy of TPF model, which is emphasized in the trajectory videos found in the supplementary material) while preserving the self-organization/vortex-merging effects that are needed to match distributional quantities such as enstrophy. In contrast, pointwise mean-squared error (MSE) trajectory fitting targets individual sample paths and, in this chaotic regime, remains accurate only over short time horizons and fails to reliably reproduce population-level statistics.",
      "page": 7,
      "index": 1,
      "width": 980,
      "height": 628
    },
    {
      "url": "assets/figures/arxiv/2605.26285v1/fig-002.webp",
      "caption": "Figure 4. Particle instabilities: Our TPF method learns population dynamics that accurately generalize across unseen Debye-length parameters in these Vlasov-Poisson instability benchmarks and match fine phase-space structure.",
      "page": 8,
      "index": 2,
      "width": 949,
      "height": 527
    }
  ]
}